pyTextPro/Tokenizer.py
pyTextPro/pad_sequences.py
pyTextPro/sequence.py
pyTextPro/text.py
pyTextPro/utils.py
pyTextPro-0.9.4.0.dist-info/METADATA
pyTextPro-0.9.4.0.dist-info/WHEEL
pyTextPro-0.9.4.0.dist-info/top_level.txt
pyTextPro-0.9.4.0.dist-info/RECORD
