Metadata-Version: 2.1
Name: pyTextPro
Version: 0.9.4.0
Summary: Python Text Processing tools
Home-page: https://blog.naver.com/lingua/222984051592
Author: Sukjae Choi
Author-email: lingua72@gmail.com
License: MIT
Platform: UNKNOWN
Requires-Python: >=3
